[

    {
      "name": "Charamel",
      "genre": "Hip-Hop",
      "artist": "Pharaoh"
    },
    {
      "name": "SKR",
      "genre": "Hip-Hop",
      "artist": "Pharaoh"
    },
    {
      "name": "AMG",
      "genre": "Hip-Hop",
      "artist": "Pharaoh"
    },
    {
      "name": "Boom-boom",
      "genre": "Hip-Hop",
      "artist": "Pharaoh"
    },
    {
      "name": "RAW 2",
      "genre": "Hip-Hop",
      "artist": "Pharaoh"
    },
    {
      "name": "Supermarket",
      "genre": "Rock",
      "artist": "Sent Molly"
    },
    {
      "name": "Non-Stop",
      "genre": "Rock",
      "artist": "Sent Molly"
    },
    {
      "name": "Party",
      "genre": "Rock",
      "artist": "Sent Molly"
    },
    {
      "name": "Emo-Punk",
      "genre": "Rock",
      "artist": "Sent Molly"
    },
    {
      "name": "Mishka",
      "genre": "Rock",
      "artist": "Sent Molly"
    },
    {
      "name": "24/7",
      "genre": "Hip-Hop",
      "artist": "Face"
    },
    {
      "name": "Salam",
      "genre": "Hip-Hop",
      "artist": "Face"
    },
    {
      "name": "Megan Fox",
      "genre": "Hip-Hop",
      "artist": "Face"
    },
    {
      "name": "Slime",
      "genre": "Hip-Hop",
      "artist": "Face"
    },
    {
      "name": "PSP",
      "genre": "Hip-Hop",
      "artist": "Face"
    },
    {
      "name": "Cosmos",
      "genre": "Rap",
      "artist": "Mnogoznaal"
    },
    {
      "name": "Minus 40",
      "genre": "Rap",
      "artist": "Mnogoznaal"
    },
    {
      "name": "AMMO",
      "genre": "Rap",
      "artist": "Mnogoznaal"
    },
    {
      "name": "Ti Typoi",
      "genre": "Rap",
      "artist": "Mnogoznaal"
    },
    {
      "name": "Z-Pam",
      "genre": "Rap",
      "artist": "Mnogoznaal"
    },
    {
      "name": "Coin",
      "genre": "Rap",
      "artist": "Lsp"
    },
    {
      "name": "Maze",
      "genre": "Rap",
      "artist": "Lsp"
    },
    {
      "name": "Pole",
      "genre": "Rap",
      "artist": "Lsp"
    },
    {
      "name": "Charamel",
      "genre": "Rap",
      "artist": "Lsp"
    },
    {
      "name": "Spit",
      "genre": "Rap",
      "artist": "Lsp"
    }


]
